insideout/__init__.py
insideout/main.py
insideout-0.0.2.dist-info/DESCRIPTION.rst
insideout-0.0.2.dist-info/METADATA
insideout-0.0.2.dist-info/RECORD
insideout-0.0.2.dist-info/WHEEL
insideout-0.0.2.dist-info/entry_points.txt
insideout-0.0.2.dist-info/metadata.json
insideout-0.0.2.dist-info/pbr.json
insideout-0.0.2.dist-info/top_level.txt
