Metadata-Version: 2.0
Name: insideout
Version: 0.0.2
Summary: A tool to develop ready-to-use python repositories.
Home-page: https://github.com/ffunenga/insideout
Author: Filipe Funenga
Author-email: fmafunenga@gmail.com
License: MIT
Platform: UNKNOWN
